{"1980": ["1980/1usenetSpam.png", "1980/text14_Plan de travail 1.jpg"], "2018": ["2018/cc.jpg", "2018/halls.png", "2018/linkedin.png"], "2015": ["2015/Boden-backpack-email-template.gif", "2015/Boden-backpack.gif", "2015/sambag.gif", "2015/swimsuit.jpg"], "2014": ["2014/food_bn_imagery_nm_q4_2014_300x250_fpad.jpg", "2014/Kate-Spade-model-with-baloons.gif", "2014/modcloth.gif", "2014/Pencil.gif", "2014/singer22.gif"], "2017": ["2017/gif.jpg", "2017/mr_porter.gif"], "2016": ["2016/bed_bath_beyond.gif", "2016/kate_spade.gif", "2016/mail.png", "2016/text13_Plan de travail 1.jpg"], "2011": ["2011/facup.jpg", "2011/ma.jpg", "2011/mtv.jpg", "2011/tb_300x250.jpg"], "2010": ["2010/1text11_Plan de travail 1.jpg", "2010/def_47c17759.jpg", "2010/Election.jpg"], "2013": ["2013/16083917436094512260.jpeg", "2013/300x250lweyw4b9v.jpg", "2013/encounters_445579g.jpg", "2013/goal.jpg", "2013/shoemint.gif", "2013/text12_Plan de travail 1.jpg"], "2012": ["2012/cycle.png", "2012/food.jpg", "2012/looper.gif", "2012/vote.jpg"], "1995": ["1995/yahoo.gif"], "1994": ["1994/1text.jpg", "1994/firstBannerAd.jpg"], "1997": ["1997/1text3.jpg", "1997/csr.gif", "1997/csr2.gif", "1997/feedbag.gif", "1997/pcsave.gif", "1997/toyota.gif"], "1996": ["1996/1text2.jpg", "1996/cyberian_home.gif", "1996/eminds_home.gif", "1996/loop.gif", "1996/new_musichome.gif"], "1999": ["1999/12060banner41ani.gif", "1999/bargain.gif", "1999/barnesandnoble.gif", "1999/desktop.gif", "1999/guinness_wired_120.gif"], "1998": ["1998/120x60_Ad1.gif", "1998/1text4_Plan de travail 1.jpg", "1998/bigstar.gif", "1998/Phoenix.gif", "1998/sun.gif", "1998/SuperBowl.gif", "1998/traveling.gif"], "1978": ["1978/firstSpam.jpg", "1978/text15_Plan de travail 1.jpg"], "2002": ["2002/100x60_banner.gif", "2002/1text6_Plan de travail 1.jpg", "2002/uproar_01.gif", "2002/WHITE-OLEANDER-nav.jpg"], "2003": ["2003/29.jpg", "2003/f113.gif", "2003/rto-subsearch3.gif"], "2000": ["2000/1text5_Plan de travail 1.jpg", "2000/4k_TFDX.gif", "2000/fr349sp.gif", "2000/intelligent468x60.gif"], "2001": ["2001/feeddaily.gif", "2001/films.gif", "2001/look.gif", "2001/mobiletimes.gif"], "2006": ["2006/10.gif", "2006/1text7_Plan de travail 1.jpg", "2006/mtvoverdrive.png"], "2007": ["2007/1text10_Plan de travail 1.jpg", "2007/ladbrokes.gif", "2007/oscar.gif"], "2004": ["2004/1361295319.jpeg", "2004/alcatel.jpg", "2004/MD-I141521.gif", "2004/squadra.gif"], "2005": ["2005/59.jpg", "2005/cup.gif", "2005/hell.jpg", "2005/meetic_2.gif"], "2008": ["2008/10.jpg", "2008/Credit.png"], "2009": ["2009/banana_republic.gif", "2009/MV5BMTk1NTE2MjYzOF5BMl5BanBnXkFtZTcwNzE4NTE1Mg@@._V1._SY140_.jpg"]}